kfp/__init__.py
kfp/cli/__init__.py
kfp/cli/__main__.py
kfp/cli/cli.py
kfp/cli/cli_test.py
kfp/cli/component.py
kfp/cli/component_test.py
kfp/cli/diagnose_me_cli.py
kfp/cli/dsl.py
kfp/cli/dsl_compile.py
kfp/cli/experiment.py
kfp/cli/output.py
kfp/cli/pipeline.py
kfp/cli/recurring_run.py
kfp/cli/run.py
kfp/cli/diagnose_me/__init__.py
kfp/cli/diagnose_me/dev_env.py
kfp/cli/diagnose_me/dev_env_test.py
kfp/cli/diagnose_me/gcp.py
kfp/cli/diagnose_me/gcp_test.py
kfp/cli/diagnose_me/kubernetes_cluster.py
kfp/cli/diagnose_me/kubernetes_cluster_test.py
kfp/cli/diagnose_me/utility.py
kfp/cli/diagnose_me/utility_test.py
kfp/cli/utils/__init__.py
kfp/cli/utils/aliased_plurals_group.py
kfp/cli/utils/aliased_plurals_group_test.py
kfp/cli/utils/deprecated_alias_group.py
kfp/cli/utils/deprecated_alias_group_test.py
kfp/cli/utils/parsing.py
kfp/cli/utils/parsing_test.py
kfp/client/__init__.py
kfp/client/auth.py
kfp/client/client.py
kfp/compiler/__init__.py
kfp/compiler/compiler.py
kfp/compiler/compiler_test.py
kfp/compiler/pipeline_spec_builder.py
kfp/compiler/pipeline_spec_builder_test.py
kfp/components/__init__.py
kfp/components/base_component.py
kfp/components/base_component_test.py
kfp/components/base_model.py
kfp/components/base_model_test.py
kfp/components/component_decorator.py
kfp/components/component_decorator_test.py
kfp/components/component_factory.py
kfp/components/component_factory_test.py
kfp/components/constants.py
kfp/components/executor.py
kfp/components/executor_main.py
kfp/components/executor_test.py
kfp/components/for_loop.py
kfp/components/for_loop_test.py
kfp/components/importer_component.py
kfp/components/importer_node.py
kfp/components/kfp_config.py
kfp/components/pipeline_channel.py
kfp/components/pipeline_channel_test.py
kfp/components/pipeline_context.py
kfp/components/pipeline_task.py
kfp/components/pipeline_task_test.py
kfp/components/placeholders.py
kfp/components/placeholders_test.py
kfp/components/python_component.py
kfp/components/structures.py
mongs_kfp-2.0.0a2.dist-info/METADATA
mongs_kfp-2.0.0a2.dist-info/WHEEL
mongs_kfp-2.0.0a2.dist-info/entry_points.txt
mongs_kfp-2.0.0a2.dist-info/top_level.txt
mongs_kfp-2.0.0a2.dist-info/RECORD
